cli/__init__.py
cli/commands.py
cli/config.py
cli/display.py
cli/interactive.py
cli/shell.py
cli/version.py
core/__init__.py
core/config.py
core/context.py
core/gitcmd.py
core/gitsy.py
entrypoint/__init__.py
entrypoint/entrypoint.py
tests/__init__.py
tests/conftest.py
tests/test_context.py
tests/test_global.py
tests/test_static.py
tests/utils.py
tests/fixtures/__init__.py
tests/fixtures/input_fixtures.py
tests/fixtures/setup_fixtures.py
tests/fixtures/state_fixtures.py
gitsy-2020.9.8.post6.dist-info/LICENSE.txt
gitsy-2020.9.8.post6.dist-info/METADATA
gitsy-2020.9.8.post6.dist-info/WHEEL
gitsy-2020.9.8.post6.dist-info/entry_points.txt
gitsy-2020.9.8.post6.dist-info/top_level.txt
gitsy-2020.9.8.post6.dist-info/RECORD
